pg_serializer/__init__.py
pg_serializer/expressions.py
pg_serializer/fields.py
pg_serializer/serializers.py
pg_serializer/settings.py
pg_serializer/utils.py
pg_serializer-0.1.3.dist-info/LICENSE
pg_serializer-0.1.3.dist-info/WHEEL
pg_serializer-0.1.3.dist-info/METADATA
pg_serializer-0.1.3.dist-info/RECORD
