Metadata-Version: 2.1
Name: pg-serializer
Version: 0.1.3
Summary: Fast serializers for Django using Postgres database
Home-page: https://gitlab.com/kozlek/pg_serializer
License: MIT
Keywords: serializer,json,postgres,drf,rest_framework
Author: Thomas Berdy
Author-email: thomas.berdy@outlook.com
Maintainer: Thomas Berdy
Maintainer-email: thomas.berdy@outlook.com
Requires-Python: >=3.8,<4.0
Classifier: Development Status :: 3 - Alpha
Classifier: License :: OSI Approved :: MIT License
Classifier: Programming Language :: Python :: 3
Classifier: Programming Language :: Python :: 3.8
Classifier: Programming Language :: Python :: 3.9
Classifier: Topic :: Database
Classifier: Topic :: Internet :: WWW/HTTP :: Dynamic Content
Classifier: Topic :: Software Development :: Libraries :: Python Modules
Requires-Dist: django
Requires-Dist: djangorestframework
Requires-Dist: psycopg2
Project-URL: Documentation, https://gitlab.com/kozlek/pg_serializer
Project-URL: Repository, https://gitlab.com/kozlek/pg_serializer
